docs/source/conf.py
protobunny/__init__.py
protobunny/__init__.py.j2
protobunny/conf.py
protobunny/exceptions.py
protobunny/helpers.py
protobunny/logger.py
protobunny/models.py
protobunny/registry.py
protobunny/utils.py
protobunny/wrapper.py
protobunny/asyncio/__init__.py
protobunny/asyncio/__init__.py.j2
protobunny/asyncio/backends/__init__.py
protobunny/asyncio/backends/mosquitto/__init__.py
protobunny/asyncio/backends/mosquitto/connection.py
protobunny/asyncio/backends/mosquitto/queues.py
protobunny/asyncio/backends/nats/__init__.py
protobunny/asyncio/backends/nats/connection.py
protobunny/asyncio/backends/nats/queues.py
protobunny/asyncio/backends/python/__init__.py
protobunny/asyncio/backends/python/connection.py
protobunny/asyncio/backends/python/queues.py
protobunny/asyncio/backends/rabbitmq/__init__.py
protobunny/asyncio/backends/rabbitmq/connection.py
protobunny/asyncio/backends/rabbitmq/queues.py
protobunny/asyncio/backends/redis/__init__.py
protobunny/asyncio/backends/redis/connection.py
protobunny/asyncio/backends/redis/queues.py
protobunny/backends/__init__.py
protobunny/backends/mosquitto/__init__.py
protobunny/backends/mosquitto/connection.py
protobunny/backends/mosquitto/queues.py
protobunny/backends/nats/__init__.py
protobunny/backends/nats/connection.py
protobunny/backends/nats/queues.py
protobunny/backends/python/__init__.py
protobunny/backends/python/connection.py
protobunny/backends/python/queues.py
protobunny/backends/rabbitmq/__init__.py
protobunny/backends/rabbitmq/connection.py
protobunny/backends/rabbitmq/queues.py
protobunny/backends/redis/__init__.py
protobunny/backends/redis/connection.py
protobunny/backends/redis/queues.py
protobunny/core/__init__.py
protobunny/core/commons/__init__.py
protobunny/core/results/__init__.py
protobunny/protobuf/protobunny/commons.proto
protobunny/protobuf/protobunny/results.proto
protobunny-0.1.2.dist-info/licenses/LICENSE
scripts/post_compile.py
tests/__init__.py
tests/conftest.py
tests/test_base.py
tests/test_config.py
tests/test_connection.py
protobunny-0.1.2.dist-info/METADATA
protobunny-0.1.2.dist-info/WHEEL
protobunny-0.1.2.dist-info/entry_points.txt
protobunny-0.1.2.dist-info/top_level.txt
protobunny-0.1.2.dist-info/RECORD
