Metadata-Version: 2.4
Name: protobunny
Version: 0.1.2
Summary: A type-safe, sync/async Python messaging library.
Author: Domenico Nappo, Sander Koelstra, Sem Mulder
Author-email: Domenico Nappo <domenico.nappo@am-flow.com>, Sander Koelstra <sander.koelstra@am-flow.com.com>, Sem Mulder <sem.mulder@am-flow.com>
Project-URL: homepage, https://am-flow.github.io/protobunny
Project-URL: repository, https://github.com/am-flow/protobunny
Project-URL: issues, https://github.com/am-flow/protobunny/issues
Keywords: messaging,protobuf,queues,mqtt,amqp,rabbitmq,redis,mosquitto,nats
Classifier: Development Status :: 3 - Alpha
Classifier: Intended Audience :: Developers
Classifier: License :: OSI Approved :: MIT License
Classifier: Programming Language :: Python :: 3.10
Classifier: Programming Language :: Python :: 3.11
Classifier: Programming Language :: Python :: 3.12
Classifier: Programming Language :: Python :: 3.13
Classifier: Topic :: Communications
Classifier: Topic :: Software Development :: Libraries :: Application Frameworks
Classifier: Topic :: System :: Distributed Computing
Requires-Python: >=3.10,<3.14
License-File: LICENSE
Requires-Dist: betterproto[compiler]<3,>=2.0.0b7
Requires-Dist: can-ada>=2.0.0
Requires-Dist: click>=8.2.1
Requires-Dist: grpcio-tools<2,>=1.62.0
Requires-Dist: tomli; python_version < "3.11"
Requires-Dist: typing-extensions; python_version < "3.11"
Provides-Extra: rabbitmq
Requires-Dist: aio-pika>=7.1.0; extra == "rabbitmq"
Provides-Extra: redis
Requires-Dist: redis<8; extra == "redis"
Provides-Extra: numpy
Requires-Dist: numpy>=1.26; extra == "numpy"
Provides-Extra: mosquitto
Requires-Dist: aiomqtt>=2.4.0; extra == "mosquitto"
Provides-Extra: nats
Requires-Dist: nats-py>=2.12.0; extra == "nats"
Dynamic: author
Dynamic: license-file
Dynamic: requires-python
